Dockerfile
LICENSE
MANIFEST.in
README.md
setup.py
containertree/__init__.py
containertree/server.py
containertree/version.py
containertree/views.py
containertree.egg-info/PKG-INFO
containertree.egg-info/SOURCES.txt
containertree.egg-info/dependency_links.txt
containertree.egg-info/entry_points.txt
containertree.egg-info/not-zip-safe
containertree.egg-info/requires.txt
containertree.egg-info/top_level.txt
containertree/client/__init__.py
containertree/client/generate.py
containertree/client/templates.py
containertree/logger/__init__.py
containertree/logger/message.py
containertree/logger/namer.py
containertree/logger/progress.py
containertree/logger/spinner.py
containertree/main/__init__.py
containertree/main/extract.py
containertree/templates/collection_tree.html
containertree/templates/container_tree.html
containertree/templates/files_tree.html
containertree/templates/heatmap-large.html
containertree/templates/heatmap.html
containertree/templates/shub_tree.html
containertree/templates/similarity_scatter.html
containertree/templates/tree.html
containertree/templates/treemap.html
containertree/tests/Dockerfile
containertree/tests/__init__.py
containertree/tests/helpers.sh
containertree/tests/test_client.sh
containertree/tests/test_collection.py
containertree/tests/test_container.py
containertree/tests/test_packages.py
containertree/tests/test_utils.py
containertree/tree/__init__.py
containertree/tree/base.py
containertree/tree/collection.py
containertree/tree/container.py
containertree/tree/loading.py
containertree/tree/node.py
containertree/utils/__init__.py
containertree/utils/docker.py
containertree/utils/fileio.py
containertree/utils/https.py